ff/__init__.py
ff/ff_ctrl.py
ff-0.0.10.dist-info/RECORD
ff-0.0.10.dist-info/METADATA
ff-0.0.10.dist-info/top_level.txt
ff-0.0.10.dist-info/WHEEL
ff-0.0.10.dist-info/DESCRIPTION.rst
ff-0.0.10.dist-info/entry_points.txt
ff-0.0.10.dist-info/metadata.json
